main.py
setup.py
jaqmc.egg-info/PKG-INFO
jaqmc.egg-info/SOURCES.txt
jaqmc.egg-info/dependency_links.txt
jaqmc.egg-info/requires.txt
jaqmc.egg-info/top_level.txt